{
  "id": "710aedf0-09aa-4170-816f-7d6e0ab472cc",
  "prevId": "00000000-0000-0000-0000-000000000000",
  "version": "7",
  "dialect": "postgresql",
  "tables": {
    "public.newsletter": {
      "name": "newsletter",
      "schema": "",
      "columns": {
        "id": {
          "name": "id",
          "type": "serial",
          "primaryKey": true,
          "notNull": true
        },
        "email": {
          "name": "email",
          "type": "text",
          "primaryKey": false,
          "notNull": true
        }
      },
      "indexes": {},
      "foreignKeys": {},
      "compositePrimaryKeys": {},
      "uniqueConstraints": {
        "newsletter_email_unique": {
          "name": "newsletter_email_unique",
          "nullsNotDistinct": false,
          "columns": [
            "email"
          ]
        }
      },
      "policies": {},
      "checkConstraints": {},
      "isRLSEnabled": false
    },
    "public.subscriptions": {
      "name": "subscriptions",
      "schema": "",
      "columns": {
        "id": {
          "name": "id",
          "type": "serial",
          "primaryKey": true,
          "notNull": true
        },
        "userId": {
          "name": "userId",
          "type": "text",
          "primaryKey": false,
          "notNull": true
        },
        "stripeSubscriptionId": {
          "name": "stripeSubscriptionId",
          "type": "text",
          "primaryKey": false,
          "notNull": true
        },
        "stripeCustomerId": {
          "name": "stripeCustomerId",
          "type": "text",
          "primaryKey": false,
          "notNull": true
        },
        "stripePriceId": {
          "name": "stripePriceId",
          "type": "text",
          "primaryKey": false,
          "notNull": true
        },
        "expires": {
          "name": "expires",
          "type": "timestamp",
          "primaryKey": false,
          "notNull": true
        }
      },
      "indexes": {},
      "foreignKeys": {
        "subscriptions_userId_user_id_fk": {
          "name": "subscriptions_userId_user_id_fk",
          "tableFrom": "subscriptions",
          "tableTo": "user",
          "columnsFrom": [
            "userId"
          ],
          "columnsTo": [
            "id"
          ],
          "onDelete": "cascade",
          "onUpdate": "no action"
        }
      },
      "compositePrimaryKeys": {},
      "uniqueConstraints": {},
      "policies": {},
      "checkConstraints": {},
      "isRLSEnabled": false
    },
    "public.user": {
      "name": "user",
      "schema": "",
      "columns": {
        "id": {
          "name": "id",
          "type": "text",
          "primaryKey": true,
          "notNull": true
        },
        "email": {
          "name": "email",
          "type": "text",
          "primaryKey": false,
          "notNull": false
        },
        "username": {
          "name": "username",
          "type": "text",
          "primaryKey": false,
          "notNull": false
        },
        "avatar": {
          "name": "avatar",
          "type": "text",
          "primaryKey": false,
          "notNull": false
        },
        "phone": {
          "name": "phone",
          "type": "text",
          "primaryKey": false,
          "notNull": false
        },
        "first_name": {
          "name": "first_name",
          "type": "text",
          "primaryKey": false,
          "notNull": false
        },
        "last_name": {
          "name": "last_name",
          "type": "text",
          "primaryKey": false,
          "notNull": false
        },
        "full_name": {
          "name": "full_name",
          "type": "text",
          "primaryKey": false,
          "notNull": false
        },
        "is_onboarded": {
          "name": "is_onboarded",
          "type": "boolean",
          "primaryKey": false,
          "notNull": false,
          "default": false
        },
        "password": {
          "name": "password",
          "type": "text",
          "primaryKey": false,
          "notNull": false
        },
        "accountStatus": {
          "name": "accountStatus",
          "type": "accountStatus",
          "typeSchema": "public",
          "primaryKey": false,
          "notNull": false,
          "default": "'onboarding'"
        },
        "stripeCustomerId": {
          "name": "stripeCustomerId",
          "type": "text",
          "primaryKey": false,
          "notNull": false
        },
        "clerk_created_at": {
          "name": "clerk_created_at",
          "type": "timestamp with time zone",
          "primaryKey": false,
          "notNull": false
        },
        "email_verified_at": {
          "name": "email_verified_at",
          "type": "timestamp with time zone",
          "primaryKey": false,
          "notNull": false
        },
        "accessed_at": {
          "name": "accessed_at",
          "type": "timestamp with time zone",
          "primaryKey": false,
          "notNull": true,
          "default": "now()"
        },
        "created_at": {
          "name": "created_at",
          "type": "timestamp with time zone",
          "primaryKey": false,
          "notNull": true,
          "default": "now()"
        },
        "updated_at": {
          "name": "updated_at",
          "type": "timestamp with time zone",
          "primaryKey": false,
          "notNull": true,
          "default": "now()"
        }
      },
      "indexes": {
        "user_email_idx": {
          "name": "user_email_idx",
          "columns": [
            {
              "expression": "email",
              "isExpression": false,
              "asc": true,
              "nulls": "last"
            }
          ],
          "isUnique": true,
          "concurrently": false,
          "method": "btree",
          "with": {}
        }
      },
      "foreignKeys": {},
      "compositePrimaryKeys": {},
      "uniqueConstraints": {
        "user_username_unique": {
          "name": "user_username_unique",
          "nullsNotDistinct": false,
          "columns": [
            "username"
          ]
        }
      },
      "policies": {},
      "checkConstraints": {},
      "isRLSEnabled": false
    },
    "public.nextauth_accounts": {
      "name": "nextauth_accounts",
      "schema": "",
      "columns": {
        "access_token": {
          "name": "access_token",
          "type": "text",
          "primaryKey": false,
          "notNull": false
        },
        "expires_at": {
          "name": "expires_at",
          "type": "integer",
          "primaryKey": false,
          "notNull": false
        },
        "id_token": {
          "name": "id_token",
          "type": "text",
          "primaryKey": false,
          "notNull": false
        },
        "provider": {
          "name": "provider",
          "type": "text",
          "primaryKey": false,
          "notNull": true
        },
        "providerAccountId": {
          "name": "providerAccountId",
          "type": "text",
          "primaryKey": false,
          "notNull": true
        },
        "refresh_token": {
          "name": "refresh_token",
          "type": "text",
          "primaryKey": false,
          "notNull": false
        },
        "scope": {
          "name": "scope",
          "type": "text",
          "primaryKey": false,
          "notNull": false
        },
        "session_state": {
          "name": "session_state",
          "type": "text",
          "primaryKey": false,
          "notNull": false
        },
        "token_type": {
          "name": "token_type",
          "type": "text",
          "primaryKey": false,
          "notNull": false
        },
        "type": {
          "name": "type",
          "type": "text",
          "primaryKey": false,
          "notNull": true
        },
        "userId": {
          "name": "userId",
          "type": "text",
          "primaryKey": false,
          "notNull": true
        }
      },
      "indexes": {},
      "foreignKeys": {
        "nextauth_accounts_userId_user_id_fk": {
          "name": "nextauth_accounts_userId_user_id_fk",
          "tableFrom": "nextauth_accounts",
          "tableTo": "user",
          "columnsFrom": [
            "userId"
          ],
          "columnsTo": [
            "id"
          ],
          "onDelete": "cascade",
          "onUpdate": "no action"
        }
      },
      "compositePrimaryKeys": {
        "nextauth_accounts_provider_providerAccountId_pk": {
          "name": "nextauth_accounts_provider_providerAccountId_pk",
          "columns": [
            "provider",
            "providerAccountId"
          ]
        }
      },
      "uniqueConstraints": {},
      "policies": {},
      "checkConstraints": {},
      "isRLSEnabled": false
    },
    "public.nextauth_authenticators": {
      "name": "nextauth_authenticators",
      "schema": "",
      "columns": {
        "counter": {
          "name": "counter",
          "type": "integer",
          "primaryKey": false,
          "notNull": true
        },
        "credentialBackedUp": {
          "name": "credentialBackedUp",
          "type": "boolean",
          "primaryKey": false,
          "notNull": true
        },
        "credentialDeviceType": {
          "name": "credentialDeviceType",
          "type": "text",
          "primaryKey": false,
          "notNull": true
        },
        "credentialID": {
          "name": "credentialID",
          "type": "text",
          "primaryKey": false,
          "notNull": true
        },
        "credentialPublicKey": {
          "name": "credentialPublicKey",
          "type": "text",
          "primaryKey": false,
          "notNull": true
        },
        "providerAccountId": {
          "name": "providerAccountId",
          "type": "text",
          "primaryKey": false,
          "notNull": true
        },
        "transports": {
          "name": "transports",
          "type": "text",
          "primaryKey": false,
          "notNull": false
        },
        "userId": {
          "name": "userId",
          "type": "text",
          "primaryKey": false,
          "notNull": true
        }
      },
      "indexes": {},
      "foreignKeys": {
        "nextauth_authenticators_userId_user_id_fk": {
          "name": "nextauth_authenticators_userId_user_id_fk",
          "tableFrom": "nextauth_authenticators",
          "tableTo": "user",
          "columnsFrom": [
            "userId"
          ],
          "columnsTo": [
            "id"
          ],
          "onDelete": "cascade",
          "onUpdate": "no action"
        }
      },
      "compositePrimaryKeys": {
        "nextauth_authenticators_userId_credentialID_pk": {
          "name": "nextauth_authenticators_userId_credentialID_pk",
          "columns": [
            "userId",
            "credentialID"
          ]
        }
      },
      "uniqueConstraints": {
        "nextauth_authenticators_credentialID_unique": {
          "name": "nextauth_authenticators_credentialID_unique",
          "nullsNotDistinct": false,
          "columns": [
            "credentialID"
          ]
        }
      },
      "policies": {},
      "checkConstraints": {},
      "isRLSEnabled": false
    },
    "public.nextauth_sessions": {
      "name": "nextauth_sessions",
      "schema": "",
      "columns": {
        "expires": {
          "name": "expires",
          "type": "timestamp",
          "primaryKey": false,
          "notNull": true
        },
        "sessionToken": {
          "name": "sessionToken",
          "type": "text",
          "primaryKey": true,
          "notNull": true
        },
        "userId": {
          "name": "userId",
          "type": "text",
          "primaryKey": false,
          "notNull": true
        }
      },
      "indexes": {},
      "foreignKeys": {
        "nextauth_sessions_userId_user_id_fk": {
          "name": "nextauth_sessions_userId_user_id_fk",
          "tableFrom": "nextauth_sessions",
          "tableTo": "user",
          "columnsFrom": [
            "userId"
          ],
          "columnsTo": [
            "id"
          ],
          "onDelete": "cascade",
          "onUpdate": "no action"
        }
      },
      "compositePrimaryKeys": {},
      "uniqueConstraints": {},
      "policies": {},
      "checkConstraints": {},
      "isRLSEnabled": false
    },
    "public.nextauth_verificationtokens": {
      "name": "nextauth_verificationtokens",
      "schema": "",
      "columns": {
        "expires": {
          "name": "expires",
          "type": "timestamp",
          "primaryKey": false,
          "notNull": true
        },
        "identifier": {
          "name": "identifier",
          "type": "text",
          "primaryKey": false,
          "notNull": true
        },
        "token": {
          "name": "token",
          "type": "text",
          "primaryKey": false,
          "notNull": true
        }
      },
      "indexes": {},
      "foreignKeys": {},
      "compositePrimaryKeys": {
        "nextauth_verificationtokens_identifier_token_pk": {
          "name": "nextauth_verificationtokens_identifier_token_pk",
          "columns": [
            "identifier",
            "token"
          ]
        }
      },
      "uniqueConstraints": {},
      "policies": {},
      "checkConstraints": {},
      "isRLSEnabled": false
    },
    "public.oidc_access_tokens": {
      "name": "oidc_access_tokens",
      "schema": "",
      "columns": {
        "id": {
          "name": "id",
          "type": "varchar(255)",
          "primaryKey": true,
          "notNull": true
        },
        "data": {
          "name": "data",
          "type": "jsonb",
          "primaryKey": false,
          "notNull": true
        },
        "expires_at": {
          "name": "expires_at",
          "type": "timestamp with time zone",
          "primaryKey": false,
          "notNull": true
        },
        "consumed_at": {
          "name": "consumed_at",
          "type": "timestamp with time zone",
          "primaryKey": false,
          "notNull": false
        },
        "user_id": {
          "name": "user_id",
          "type": "text",
          "primaryKey": false,
          "notNull": true
        },
        "client_id": {
          "name": "client_id",
          "type": "varchar(255)",
          "primaryKey": false,
          "notNull": true
        },
        "grant_id": {
          "name": "grant_id",
          "type": "varchar(255)",
          "primaryKey": false,
          "notNull": false
        },
        "accessed_at": {
          "name": "accessed_at",
          "type": "timestamp with time zone",
          "primaryKey": false,
          "notNull": true,
          "default": "now()"
        },
        "created_at": {
          "name": "created_at",
          "type": "timestamp with time zone",
          "primaryKey": false,
          "notNull": true,
          "default": "now()"
        },
        "updated_at": {
          "name": "updated_at",
          "type": "timestamp with time zone",
          "primaryKey": false,
          "notNull": true,
          "default": "now()"
        }
      },
      "indexes": {},
      "foreignKeys": {
        "oidc_access_tokens_user_id_user_id_fk": {
          "name": "oidc_access_tokens_user_id_user_id_fk",
          "tableFrom": "oidc_access_tokens",
          "tableTo": "user",
          "columnsFrom": [
            "user_id"
          ],
          "columnsTo": [
            "id"
          ],
          "onDelete": "cascade",
          "onUpdate": "no action"
        }
      },
      "compositePrimaryKeys": {},
      "uniqueConstraints": {},
      "policies": {},
      "checkConstraints": {},
      "isRLSEnabled": false
    },
    "public.oidc_authorization_codes": {
      "name": "oidc_authorization_codes",
      "schema": "",
      "columns": {
        "id": {
          "name": "id",
          "type": "varchar(255)",
          "primaryKey": true,
          "notNull": true
        },
        "data": {
          "name": "data",
          "type": "jsonb",
          "primaryKey": false,
          "notNull": true
        },
        "expires_at": {
          "name": "expires_at",
          "type": "timestamp with time zone",
          "primaryKey": false,
          "notNull": true
        },
        "consumed_at": {
          "name": "consumed_at",
          "type": "timestamp with time zone",
          "primaryKey": false,
          "notNull": false
        },
        "user_id": {
          "name": "user_id",
          "type": "text",
          "primaryKey": false,
          "notNull": true
        },
        "client_id": {
          "name": "client_id",
          "type": "varchar(255)",
          "primaryKey": false,
          "notNull": true
        },
        "grant_id": {
          "name": "grant_id",
          "type": "varchar(255)",
          "primaryKey": false,
          "notNull": false
        },
        "accessed_at": {
          "name": "accessed_at",
          "type": "timestamp with time zone",
          "primaryKey": false,
          "notNull": true,
          "default": "now()"
        },
        "created_at": {
          "name": "created_at",
          "type": "timestamp with time zone",
          "primaryKey": false,
          "notNull": true,
          "default": "now()"
        },
        "updated_at": {
          "name": "updated_at",
          "type": "timestamp with time zone",
          "primaryKey": false,
          "notNull": true,
          "default": "now()"
        }
      },
      "indexes": {},
      "foreignKeys": {
        "oidc_authorization_codes_user_id_user_id_fk": {
          "name": "oidc_authorization_codes_user_id_user_id_fk",
          "tableFrom": "oidc_authorization_codes",
          "tableTo": "user",
          "columnsFrom": [
            "user_id"
          ],
          "columnsTo": [
            "id"
          ],
          "onDelete": "cascade",
          "onUpdate": "no action"
        }
      },
      "compositePrimaryKeys": {},
      "uniqueConstraints": {},
      "policies": {},
      "checkConstraints": {},
      "isRLSEnabled": false
    },
    "public.oidc_clients": {
      "name": "oidc_clients",
      "schema": "",
      "columns": {
        "id": {
          "name": "id",
          "type": "varchar(255)",
          "primaryKey": true,
          "notNull": true
        },
        "name": {
          "name": "name",
          "type": "text",
          "primaryKey": false,
          "notNull": true
        },
        "description": {
          "name": "description",
          "type": "text",
          "primaryKey": false,
          "notNull": false
        },
        "client_secret": {
          "name": "client_secret",
          "type": "varchar(255)",
          "primaryKey": false,
          "notNull": false
        },
        "redirect_uris": {
          "name": "redirect_uris",
          "type": "text[]",
          "primaryKey": false,
          "notNull": true
        },
        "grants": {
          "name": "grants",
          "type": "text[]",
          "primaryKey": false,
          "notNull": true
        },
        "response_types": {
          "name": "response_types",
          "type": "text[]",
          "primaryKey": false,
          "notNull": true
        },
        "scopes": {
          "name": "scopes",
          "type": "text[]",
          "primaryKey": false,
          "notNull": true
        },
        "token_endpoint_auth_method": {
          "name": "token_endpoint_auth_method",
          "type": "varchar(20)",
          "primaryKey": false,
          "notNull": false
        },
        "application_type": {
          "name": "application_type",
          "type": "varchar(20)",
          "primaryKey": false,
          "notNull": false
        },
        "client_uri": {
          "name": "client_uri",
          "type": "text",
          "primaryKey": false,
          "notNull": false
        },
        "logo_uri": {
          "name": "logo_uri",
          "type": "text",
          "primaryKey": false,
          "notNull": false
        },
        "policy_uri": {
          "name": "policy_uri",
          "type": "text",
          "primaryKey": false,
          "notNull": false
        },
        "tos_uri": {
          "name": "tos_uri",
          "type": "text",
          "primaryKey": false,
          "notNull": false
        },
        "is_first_party": {
          "name": "is_first_party",
          "type": "boolean",
          "primaryKey": false,
          "notNull": false,
          "default": false
        },
        "accessed_at": {
          "name": "accessed_at",
          "type": "timestamp with time zone",
          "primaryKey": false,
          "notNull": true,
          "default": "now()"
        },
        "created_at": {
          "name": "created_at",
          "type": "timestamp with time zone",
          "primaryKey": false,
          "notNull": true,
          "default": "now()"
        },
        "updated_at": {
          "name": "updated_at",
          "type": "timestamp with time zone",
          "primaryKey": false,
          "notNull": true,
          "default": "now()"
        }
      },
      "indexes": {},
      "foreignKeys": {},
      "compositePrimaryKeys": {},
      "uniqueConstraints": {},
      "policies": {},
      "checkConstraints": {},
      "isRLSEnabled": false
    },
    "public.oidc_consents": {
      "name": "oidc_consents",
      "schema": "",
      "columns": {
        "user_id": {
          "name": "user_id",
          "type": "text",
          "primaryKey": false,
          "notNull": true
        },
        "client_id": {
          "name": "client_id",
          "type": "varchar(255)",
          "primaryKey": false,
          "notNull": true
        },
        "scopes": {
          "name": "scopes",
          "type": "text[]",
          "primaryKey": false,
          "notNull": true
        },
        "expires_at": {
          "name": "expires_at",
          "type": "timestamp with time zone",
          "primaryKey": false,
          "notNull": false
        },
        "accessed_at": {
          "name": "accessed_at",
          "type": "timestamp with time zone",
          "primaryKey": false,
          "notNull": true,
          "default": "now()"
        },
        "created_at": {
          "name": "created_at",
          "type": "timestamp with time zone",
          "primaryKey": false,
          "notNull": true,
          "default": "now()"
        },
        "updated_at": {
          "name": "updated_at",
          "type": "timestamp with time zone",
          "primaryKey": false,
          "notNull": true,
          "default": "now()"
        }
      },
      "indexes": {},
      "foreignKeys": {
        "oidc_consents_user_id_user_id_fk": {
          "name": "oidc_consents_user_id_user_id_fk",
          "tableFrom": "oidc_consents",
          "tableTo": "user",
          "columnsFrom": [
            "user_id"
          ],
          "columnsTo": [
            "id"
          ],
          "onDelete": "cascade",
          "onUpdate": "no action"
        },
        "oidc_consents_client_id_oidc_clients_id_fk": {
          "name": "oidc_consents_client_id_oidc_clients_id_fk",
          "tableFrom": "oidc_consents",
          "tableTo": "oidc_clients",
          "columnsFrom": [
            "client_id"
          ],
          "columnsTo": [
            "id"
          ],
          "onDelete": "cascade",
          "onUpdate": "no action"
        }
      },
      "compositePrimaryKeys": {
        "oidc_consents_user_id_client_id_pk": {
          "name": "oidc_consents_user_id_client_id_pk",
          "columns": [
            "user_id",
            "client_id"
          ]
        }
      },
      "uniqueConstraints": {},
      "policies": {},
      "checkConstraints": {},
      "isRLSEnabled": false
    },
    "public.oidc_device_codes": {
      "name": "oidc_device_codes",
      "schema": "",
      "columns": {
        "id": {
          "name": "id",
          "type": "varchar(255)",
          "primaryKey": true,
          "notNull": true
        },
        "data": {
          "name": "data",
          "type": "jsonb",
          "primaryKey": false,
          "notNull": true
        },
        "expires_at": {
          "name": "expires_at",
          "type": "timestamp with time zone",
          "primaryKey": false,
          "notNull": true
        },
        "consumed_at": {
          "name": "consumed_at",
          "type": "timestamp with time zone",
          "primaryKey": false,
          "notNull": false
        },
        "user_id": {
          "name": "user_id",
          "type": "text",
          "primaryKey": false,
          "notNull": false
        },
        "client_id": {
          "name": "client_id",
          "type": "varchar(255)",
          "primaryKey": false,
          "notNull": true
        },
        "grant_id": {
          "name": "grant_id",
          "type": "varchar(255)",
          "primaryKey": false,
          "notNull": false
        },
        "user_code": {
          "name": "user_code",
          "type": "varchar(255)",
          "primaryKey": false,
          "notNull": false
        },
        "accessed_at": {
          "name": "accessed_at",
          "type": "timestamp with time zone",
          "primaryKey": false,
          "notNull": true,
          "default": "now()"
        },
        "created_at": {
          "name": "created_at",
          "type": "timestamp with time zone",
          "primaryKey": false,
          "notNull": true,
          "default": "now()"
        },
        "updated_at": {
          "name": "updated_at",
          "type": "timestamp with time zone",
          "primaryKey": false,
          "notNull": true,
          "default": "now()"
        }
      },
      "indexes": {},
      "foreignKeys": {
        "oidc_device_codes_user_id_user_id_fk": {
          "name": "oidc_device_codes_user_id_user_id_fk",
          "tableFrom": "oidc_device_codes",
          "tableTo": "user",
          "columnsFrom": [
            "user_id"
          ],
          "columnsTo": [
            "id"
          ],
          "onDelete": "cascade",
          "onUpdate": "no action"
        }
      },
      "compositePrimaryKeys": {},
      "uniqueConstraints": {},
      "policies": {},
      "checkConstraints": {},
      "isRLSEnabled": false
    },
    "public.oidc_grants": {
      "name": "oidc_grants",
      "schema": "",
      "columns": {
        "id": {
          "name": "id",
          "type": "varchar(255)",
          "primaryKey": true,
          "notNull": true
        },
        "data": {
          "name": "data",
          "type": "jsonb",
          "primaryKey": false,
          "notNull": true
        },
        "expires_at": {
          "name": "expires_at",
          "type": "timestamp with time zone",
          "primaryKey": false,
          "notNull": true
        },
        "consumed_at": {
          "name": "consumed_at",
          "type": "timestamp with time zone",
          "primaryKey": false,
          "notNull": false
        },
        "user_id": {
          "name": "user_id",
          "type": "text",
          "primaryKey": false,
          "notNull": true
        },
        "client_id": {
          "name": "client_id",
          "type": "varchar(255)",
          "primaryKey": false,
          "notNull": true
        },
        "accessed_at": {
          "name": "accessed_at",
          "type": "timestamp with time zone",
          "primaryKey": false,
          "notNull": true,
          "default": "now()"
        },
        "created_at": {
          "name": "created_at",
          "type": "timestamp with time zone",
          "primaryKey": false,
          "notNull": true,
          "default": "now()"
        },
        "updated_at": {
          "name": "updated_at",
          "type": "timestamp with time zone",
          "primaryKey": false,
          "notNull": true,
          "default": "now()"
        }
      },
      "indexes": {},
      "foreignKeys": {
        "oidc_grants_user_id_user_id_fk": {
          "name": "oidc_grants_user_id_user_id_fk",
          "tableFrom": "oidc_grants",
          "tableTo": "user",
          "columnsFrom": [
            "user_id"
          ],
          "columnsTo": [
            "id"
          ],
          "onDelete": "cascade",
          "onUpdate": "no action"
        }
      },
      "compositePrimaryKeys": {},
      "uniqueConstraints": {},
      "policies": {},
      "checkConstraints": {},
      "isRLSEnabled": false
    },
    "public.oidc_interactions": {
      "name": "oidc_interactions",
      "schema": "",
      "columns": {
        "id": {
          "name": "id",
          "type": "varchar(255)",
          "primaryKey": true,
          "notNull": true
        },
        "data": {
          "name": "data",
          "type": "jsonb",
          "primaryKey": false,
          "notNull": true
        },
        "expires_at": {
          "name": "expires_at",
          "type": "timestamp with time zone",
          "primaryKey": false,
          "notNull": true
        },
        "accessed_at": {
          "name": "accessed_at",
          "type": "timestamp with time zone",
          "primaryKey": false,
          "notNull": true,
          "default": "now()"
        },
        "created_at": {
          "name": "created_at",
          "type": "timestamp with time zone",
          "primaryKey": false,
          "notNull": true,
          "default": "now()"
        },
        "updated_at": {
          "name": "updated_at",
          "type": "timestamp with time zone",
          "primaryKey": false,
          "notNull": true,
          "default": "now()"
        }
      },
      "indexes": {},
      "foreignKeys": {},
      "compositePrimaryKeys": {},
      "uniqueConstraints": {},
      "policies": {},
      "checkConstraints": {},
      "isRLSEnabled": false
    },
    "public.oidc_refresh_tokens": {
      "name": "oidc_refresh_tokens",
      "schema": "",
      "columns": {
        "id": {
          "name": "id",
          "type": "varchar(255)",
          "primaryKey": true,
          "notNull": true
        },
        "data": {
          "name": "data",
          "type": "jsonb",
          "primaryKey": false,
          "notNull": true
        },
        "expires_at": {
          "name": "expires_at",
          "type": "timestamp with time zone",
          "primaryKey": false,
          "notNull": true
        },
        "consumed_at": {
          "name": "consumed_at",
          "type": "timestamp with time zone",
          "primaryKey": false,
          "notNull": false
        },
        "user_id": {
          "name": "user_id",
          "type": "text",
          "primaryKey": false,
          "notNull": true
        },
        "client_id": {
          "name": "client_id",
          "type": "varchar(255)",
          "primaryKey": false,
          "notNull": true
        },
        "grant_id": {
          "name": "grant_id",
          "type": "varchar(255)",
          "primaryKey": false,
          "notNull": false
        },
        "accessed_at": {
          "name": "accessed_at",
          "type": "timestamp with time zone",
          "primaryKey": false,
          "notNull": true,
          "default": "now()"
        },
        "created_at": {
          "name": "created_at",
          "type": "timestamp with time zone",
          "primaryKey": false,
          "notNull": true,
          "default": "now()"
        },
        "updated_at": {
          "name": "updated_at",
          "type": "timestamp with time zone",
          "primaryKey": false,
          "notNull": true,
          "default": "now()"
        }
      },
      "indexes": {},
      "foreignKeys": {
        "oidc_refresh_tokens_user_id_user_id_fk": {
          "name": "oidc_refresh_tokens_user_id_user_id_fk",
          "tableFrom": "oidc_refresh_tokens",
          "tableTo": "user",
          "columnsFrom": [
            "user_id"
          ],
          "columnsTo": [
            "id"
          ],
          "onDelete": "cascade",
          "onUpdate": "no action"
        }
      },
      "compositePrimaryKeys": {},
      "uniqueConstraints": {},
      "policies": {},
      "checkConstraints": {},
      "isRLSEnabled": false
    },
    "public.oidc_sessions": {
      "name": "oidc_sessions",
      "schema": "",
      "columns": {
        "id": {
          "name": "id",
          "type": "varchar(255)",
          "primaryKey": true,
          "notNull": true
        },
        "data": {
          "name": "data",
          "type": "jsonb",
          "primaryKey": false,
          "notNull": true
        },
        "expires_at": {
          "name": "expires_at",
          "type": "timestamp with time zone",
          "primaryKey": false,
          "notNull": true
        },
        "user_id": {
          "name": "user_id",
          "type": "text",
          "primaryKey": false,
          "notNull": true
        },
        "accessed_at": {
          "name": "accessed_at",
          "type": "timestamp with time zone",
          "primaryKey": false,
          "notNull": true,
          "default": "now()"
        },
        "created_at": {
          "name": "created_at",
          "type": "timestamp with time zone",
          "primaryKey": false,
          "notNull": true,
          "default": "now()"
        },
        "updated_at": {
          "name": "updated_at",
          "type": "timestamp with time zone",
          "primaryKey": false,
          "notNull": true,
          "default": "now()"
        }
      },
      "indexes": {},
      "foreignKeys": {
        "oidc_sessions_user_id_user_id_fk": {
          "name": "oidc_sessions_user_id_user_id_fk",
          "tableFrom": "oidc_sessions",
          "tableTo": "user",
          "columnsFrom": [
            "user_id"
          ],
          "columnsTo": [
            "id"
          ],
          "onDelete": "cascade",
          "onUpdate": "no action"
        }
      },
      "compositePrimaryKeys": {},
      "uniqueConstraints": {},
      "policies": {},
      "checkConstraints": {},
      "isRLSEnabled": false
    }
  },
  "enums": {
    "public.accountStatus": {
      "name": "accountStatus",
      "schema": "public",
      "values": [
        "suspended",
        "disabled",
        "active",
        "onboarding"
      ]
    },
    "public.role": {
      "name": "role",
      "schema": "public",
      "values": [
        "user",
        "admin",
        "member"
      ]
    }
  },
  "schemas": {},
  "sequences": {},
  "roles": {},
  "policies": {},
  "views": {},
  "_meta": {
    "columns": {},
    "schemas": {},
    "tables": {}
  }
}